OpenCopilot.py
cli.py
Agents/__init__.py
Agents/Executor/__init__.py
Agents/Executor/executor.py
Agents/Executor/prompts.py
Env/__init__.py
Env/base_env.py
Env/python_executor.py
Env/shell.py
Env/tests/__init__.py
Env/tests/test_python_executor.py
Env/tests/test_shell_executor.py
Tools/__init__.py
Tools/file_task.py
Tools/system_details.py
Tools/tool_dir.json
Tools/tool_manager.py
Tools/userinp.py
Tools/web_loader.py
Tools/web_search.py
Utils/__init__.py
Utils/executor_utils.py
Utils/ter_interface.py
llm_interface/__init__.py
llm_interface/llm.py
pikoai-0.1.33.dist-info/licenses/LICENSE
pikoai-0.1.33.dist-info/METADATA
pikoai-0.1.33.dist-info/WHEEL
pikoai-0.1.33.dist-info/entry_points.txt
pikoai-0.1.33.dist-info/top_level.txt
pikoai-0.1.33.dist-info/RECORD
