Metadata-Version: 2.4
Name: PikoAi
Version: 0.1.33
Summary: An AI-powered task automation tool
Home-page: https://github.com/nihaaaar22/OS-Assistant
Author: Nihar S
Author-email: nihar.sr22@gmail.com
Classifier: Programming Language :: Python :: 3
Classifier: License :: OSI Approved :: MIT License
Classifier: Operating System :: OS Independent
Requires-Python: >=3.8
License-File: LICENSE
Requires-Dist: python-dotenv>=1.0.1
Requires-Dist: openai>=1.58.1
Requires-Dist: groq>=0.22.0
Requires-Dist: requests>=2.32.3
Requires-Dist: pdfplumber>=0.11.4
Requires-Dist: beautifulsoup4>=4.13.4
Requires-Dist: duckduckgo_search>=7.4.2
Requires-Dist: rich>=13.9.4
Requires-Dist: mistralai>=1.2.5
Requires-Dist: click>=8.1.8
Requires-Dist: httpx>=0.28.1
Requires-Dist: psutil>=5.9.8
Requires-Dist: inquirer>=3.1.3
Requires-Dist: litellm
Requires-Dist: prompt_toolkit>=3.0.43
Requires-Dist: PyPDF2
Requires-Dist: python-docx
Requires-Dist: yaspin==3.1.0
Dynamic: author
Dynamic: author-email
Dynamic: classifier
Dynamic: description
Dynamic: description-content-type
Dynamic: home-page
Dynamic: license-file
Dynamic: requires-dist
Dynamic: requires-python
Dynamic: summary
